my_weather_forcast/Precipitation_Forecast.py
my_weather_forcast/__init__.py
my_weather_forcast/get_countrys.py
my_weather_forecast-1.0.dist-info/METADATA
my_weather_forecast-1.0.dist-info/WHEEL
my_weather_forecast-1.0.dist-info/top_level.txt
my_weather_forecast-1.0.dist-info/RECORD
