Metadata-Version: 2.1
Name: my-weather-forecast
Version: 1.0
Summary: 制作农作物主产区天气图片
Home-page: UNKNOWN
Author: Wang Zhao Qiang
Author-email: 349558455@qq.com
License: UNKNOWN
Platform: UNKNOWN
